mycalc/calculator.py
dainKim-1.0.1.dist-info/METADATA
dainKim-1.0.1.dist-info/WHEEL
dainKim-1.0.1.dist-info/top_level.txt
dainKim-1.0.1.dist-info/RECORD
