Metadata-Version: 2.1
Name: dainKim
Version: 1.0.1
Summary: nice calc
Home-page: 
Download-URL: 
Author: dain
License: UNKNOWN
Platform: UNKNOWN
Classifier: Programming Language :: Python :: 3
